{"_ts":[1488346062,1488389298,1488432934,1488476327,1488520020,1488563578],"_r":{"breakdown":{"html":{"bytes":[16350,16339,16316,16562,16273,16305],"requests":[4,4,4,5,4,4]},"js":{"bytes":[180631,173211,173160,173211,173414,173411],"requests":[9,8,8,8,8,8]},"css":{"bytes":[63744,63743,63744,63743,63744,63741],"requests":[3,3,3,3,3,3]},"image":{"bytes":[357790,361649,361037,355592,699896,359988],"requests":[32,32,32,32,38,32]},"flash":{"bytes":[0,0,0,0,0,0],"requests":[0,0,0,0,0,0]},"font":{"bytes":[89301,89298,89301,89298,89301,89298],"requests":[3,3,3,3,3,3]},"other":{"bytes":[0,0,0,0,0,0],"requests":[0,0,0,0,0,0]}},"date":[1488346062,1488389298,1488432934,1488476327,1488520020,1488563578],"domElements":[1313,1306,1306,1328,null,1306],"domInteractive":[1902,2769,1844,2204,null,2648],"firstPaint":[1540,2132,1529,1938,null,2163],"fullyLoaded":[3259,4492,3267,3496,null,4753],"id":["170301_MN_AEZ","170301_P3_12Z1","170302_4B_9Z0","170302_DC_13QX","170303_8R_A4K","170303_EV_5KJS"],"loadTime":[3215,4332,3146,3372,null,4614],"render":[674,2599,1789,2292,null,2604],"SpeedIndex":[2867,4038,2828,3121,null,4368],"TTFB":[807,883,706,789,null,526],"videoFrames":[[{"_t":0,"_vc":0},{"_t":700,"_vc":0},{"_t":800,"_vc":0},{"_t":900,"_vc":0},{"_t":1100,"_vc":0},{"_t":1300,"_vc":0},{"_t":1400,"_vc":0},{"_t":1500,"_vc":0},{"_t":1700,"_vc":10},{"_t":1900,"_vc":10},{"_t":2100,"_vc":10},{"_t":2300,"_vc":10},{"_t":2400,"_vc":10},{"_t":2500,"_vc":10},{"_t":2700,"_vc":22},{"_t":2900,"_vc":22},{"_t":3100,"_vc":99},{"_t":3200,"_vc":99},{"_t":3300,"_vc":99},{"_t":3500,"_vc":99},{"_t":3600,"_vc":99},{"_t":3700,"_vc":100},{"_t":3900,"_vc":99},{"_t":4300,"_vc":100},{"_t":4500,"_vc":100},{"_t":5000,"_vc":100}],[{"_t":0,"_vc":0},{"_t":2600,"_vc":8},{"_t":3000,"_vc":8},{"_t":4000,"_vc":20},{"_t":4200,"_vc":100},{"_t":4400,"_vc":99},{"_t":4500,"_vc":100},{"_t":5000,"_vc":99},{"_t":5500,"_vc":100},{"_t":6100,"_vc":99},{"_t":6600,"_vc":100}],[{"_t":0,"_vc":0},{"_t":1800,"_vc":8},{"_t":2500,"_vc":20},{"_t":2700,"_vc":20},{"_t":3000,"_vc":99},{"_t":3300,"_vc":100},{"_t":3800,"_vc":99},{"_t":4400,"_vc":100},{"_t":5000,"_vc":99},{"_t":5400,"_vc":100}],[{"_t":0,"_vc":0},{"_t":2300,"_vc":8},{"_t":2500,"_vc":9},{"_t":3000,"_vc":20},{"_t":3200,"_vc":89},{"_t":3400,"_vc":100},{"_t":3800,"_vc":100},{"_t":4200,"_vc":100},{"_t":4800,"_vc":100},{"_t":5300,"_vc":100}],[{"_t":0,"_vc":0},{"_t":4000,"_vc":8},{"_t":7000,"_vc":78},{"_t":9000,"_vc":80},{"_t":10000,"_vc":80},{"_t":11000,"_vc":80},{"_t":14000,"_vc":76},{"_t":15000,"_vc":81},{"_t":16000,"_vc":81},{"_t":17000,"_vc":78},{"_t":19000,"_vc":78},{"_t":20000,"_vc":78},{"_t":23000,"_vc":78},{"_t":24000,"_vc":78},{"_t":25000,"_vc":79},{"_t":26000,"_vc":93},{"_t":27000,"_vc":95},{"_t":28000,"_vc":100},{"_t":29000,"_vc":100},{"_t":30000,"_vc":99},{"_t":32000,"_vc":99},{"_t":34000,"_vc":99},{"_t":35000,"_vc":99},{"_t":37000,"_vc":84},{"_t":38000,"_vc":81},{"_t":39000,"_vc":73},{"_t":40000,"_vc":73},{"_t":41000,"_vc":73},{"_t":44000,"_vc":73},{"_t":45000,"_vc":73},{"_t":48000,"_vc":82},{"_t":49000,"_vc":80},{"_t":50000,"_vc":80},{"_t":54000,"_vc":80},{"_t":55000,"_vc":80},{"_t":59000,"_vc":81},{"_t":60000,"_vc":78},{"_t":64000,"_vc":78},{"_t":65000,"_vc":78},{"_t":68000,"_vc":78},{"_t":69000,"_vc":78},{"_t":70000,"_vc":80},{"_t":71000,"_vc":99},{"_t":74000,"_vc":99},{"_t":75000,"_vc":99},{"_t":76000,"_vc":99},{"_t":79000,"_vc":99},{"_t":80000,"_vc":99},{"_t":81000,"_vc":100},{"_t":82000,"_vc":74},{"_t":83000,"_vc":73},{"_t":84000,"_vc":73},{"_t":85000,"_vc":73},{"_t":89000,"_vc":73},{"_t":90000,"_vc":73},{"_t":93000,"_vc":82},{"_t":94000,"_vc":80},{"_t":95000,"_vc":80},{"_t":99000,"_vc":80},{"_t":100000,"_vc":80},{"_t":103000,"_vc":80},{"_t":104000,"_vc":82},{"_t":105000,"_vc":78},{"_t":109000,"_vc":78},{"_t":110000,"_vc":78},{"_t":112000,"_vc":78},{"_t":114000,"_vc":78},{"_t":115000,"_vc":83},{"_t":116000,"_vc":99},{"_t":119000,"_vc":99},{"_t":120000,"_vc":99},{"_t":121000,"_vc":100}],[{"_t":0,"_vc":0},{"_t":2600,"_vc":8},{"_t":3900,"_vc":20},{"_t":4600,"_vc":100},{"_t":5000,"_vc":99},{"_t":5500,"_vc":100},{"_t":6000,"_vc":99},{"_t":6700,"_vc":100}]],"visualComplete":[3686,4204,2991,3400,null,4600]}}